baidu_ai_search_mcp/__init__.py
baidu_ai_search_mcp/__main__.py
baidu_ai_search_mcp/client.py
baidu_ai_search_mcp/server.py
baidu_ai_search_mcp-0.1.0.dist-info/METADATA
baidu_ai_search_mcp-0.1.0.dist-info/WHEEL
baidu_ai_search_mcp-0.1.0.dist-info/entry_points.txt
baidu_ai_search_mcp-0.1.0.dist-info/licenses/LICENSE
baidu_ai_search_mcp-0.1.0.dist-info/RECORD
