Metadata-Version: 2.4
Name: baidu-ai-search-mcp
Version: 0.1.0
Summary: 百度AI搜索 MCP服务 - 在Cursor等支持MCP的应用中使用百度AI搜索功能
Project-URL: Homepage, https://github.com/yourusername/baidu-ai-search-mcp
Project-URL: Repository, https://github.com/yourusername/baidu-ai-search-mcp
Project-URL: Issues, https://github.com/yourusername/baidu-ai-search-mcp/issues
Author-email: whw0723 <774633753@qq.com>
License-Expression: MIT
License-File: LICENSE
Keywords: ai,baidu,cursor,mcp,search
Classifier: Development Status :: 4 - Beta
Classifier: Intended Audience :: Developers
Classifier: License :: OSI Approved :: MIT License
Classifier: Programming Language :: Python :: 3
Classifier: Programming Language :: Python :: 3.10
Classifier: Programming Language :: Python :: 3.11
Classifier: Programming Language :: Python :: 3.12
Requires-Python: >=3.10
Requires-Dist: httpx>=0.27.0
Requires-Dist: mcp>=1.0.0
Requires-Dist: python-dotenv>=1.0.0
